pyfrench/__init__.py
pyfrench/aléatoire.py
pyfrench/logique.py
pyfrench/maths.py
pyfrench/retour.py
pyfrench/terminal.py
pyfrench/win10toast/__init__.py
pyfrench/win10toast/__main__.py
pyfrench-0.3.2.dist-info/METADATA
pyfrench-0.3.2.dist-info/WHEEL
pyfrench-0.3.2.dist-info/top_level.txt
pyfrench-0.3.2.dist-info/RECORD
